CHANGES.rst
LICENSE
MANIFEST.in
README.rst
setup.cfg
setup.py
docs/CHANGES.rst
docs/README.rst
docs/conf.py
docs/index.rst
docs/_static/.keep
docs/_templates/.keep
src/C99/__about__.py
src/C99/__init__.py
src/C99/inttypes.h
src/C99/stdint.h
src/C99.egg-info/PKG-INFO
src/C99.egg-info/SOURCES.txt
src/C99.egg-info/dependency_links.txt
src/C99.egg-info/not-zip-safe
src/C99.egg-info/requires.txt
src/C99.egg-info/top_level.txt
tests/__init__.py
tests/__main__.py