Metadata-Version: 2.1
Name: C99
Version: 1.0.4
Summary: C99 headers and libraries that are missing from the C compilers for Python2.
Home-page: https://pypi.org/project/C99/
Author: Adam Karpierz
Author-email: adam@karpierz.net
Maintainer: Adam Karpierz
Maintainer-email: adam@karpierz.net
License: zlib/libpng License ; https://opensource.org/licenses/Zlib
Download-URL: https://pypi.org/project/C99/
Project-URL: Documentation, https://C99.readthedocs.io/
Project-URL: Source, https://github.com/karpierz/C99/
Keywords: C99,C,C++
Platform: any
Classifier: Development Status :: 5 - Production/Stable
Classifier: Intended Audience :: Developers
Classifier: License :: OSI Approved :: zlib/libpng License
Classifier: Operating System :: OS Independent
Classifier: Natural Language :: Polish
Classifier: Programming Language :: Python
Classifier: Programming Language :: Python :: 2
Classifier: Programming Language :: Python :: 2.7
Classifier: Programming Language :: Python :: 2 :: Only
Classifier: Programming Language :: Python :: Implementation :: CPython
Classifier: Programming Language :: Python :: Implementation :: Stackless
Classifier: Programming Language :: C
Classifier: Topic :: Software Development :: Libraries :: Python Modules
Requires-Python: ==2.7.*
Provides-Extra: doc
Provides-Extra: test
